MANIFEST.in
README.rst
distribute_setup.py
setup.cfg
setup.py
ibidem/__init__.py
ibidem/util/__init__.py
ibidem/util/downloader.py
ibidem/util/workpool.py
ibidem_util.egg-info/PKG-INFO
ibidem_util.egg-info/SOURCES.txt
ibidem_util.egg-info/dependency_links.txt
ibidem_util.egg-info/namespace_packages.txt
ibidem_util.egg-info/top_level.txt
ibidem_util.egg-info/zip-safe