Metadata-Version: 1.0
Name: ibidem-util
Version: 1.1.1
Summary: Ibidem utilities
Home-page: http://ibidem.homeip.net/Misc/wiki/Utils
Author: Morten Lied Johansen
Author-email: mortenjo@ifi.uio.no
License: LGPL
Keywords: ibidem util
Platform: UNKNOWN
Classifier: Development Status :: 5 - Production/Stable
Classifier: Intended Audience :: Developers
Classifier: License :: OSI Approved :: GNU Library or Lesser General Public License (LGPL)
Classifier: Operating System :: OS Independent
Classifier: Programming Language :: Python
Classifier: Topic :: Software Development :: Libraries :: Python Modules
